jupyterpidaq_menu/__init__.py
jupyterpidaq_menu/_version.py
jupyterpidaq_menu-0.1.0.data/data/share/jupyter/labextensions/jupyterpidaq-menu/package.json
jupyterpidaq_menu-0.1.0.data/data/share/jupyter/labextensions/jupyterpidaq-menu/static/509.af550bda5eb2986cd553.js
jupyterpidaq_menu-0.1.0.data/data/share/jupyter/labextensions/jupyterpidaq-menu/static/728.9a4912b775fbf981d50c.js
jupyterpidaq_menu-0.1.0.data/data/share/jupyter/labextensions/jupyterpidaq-menu/static/remoteEntry.18c46976fe1f67cdd481.js
jupyterpidaq_menu-0.1.0.data/data/share/jupyter/labextensions/jupyterpidaq-menu/static/style.js
jupyterpidaq_menu-0.1.0.data/data/share/jupyter/labextensions/jupyterpidaq-menu/static/third-party-licenses.json
jupyterpidaq_menu-0.1.0.data/data/share/jupyter/labextensions/jupyterpidaq-menu/install.json
jupyterpidaq_menu-0.1.0.dist-info/METADATA
jupyterpidaq_menu-0.1.0.dist-info/WHEEL
jupyterpidaq_menu-0.1.0.dist-info/licenses/LICENSE
jupyterpidaq_menu-0.1.0.dist-info/licenses/LICENSE.txt
jupyterpidaq_menu-0.1.0.dist-info/RECORD
