Metadata-Version: 2.3
Name: jupyterpidaq_menu
Version: 0.1.0
Dynamic: Keywords
Summary: Convenience menu for JupyterPiDAQ that runs in Jupyter Lab and Notebook >=7.
Project-URL: Homepage, https://github.com/JupyterPhysSciLab/JupyterPiDAQ_Menu.git
Project-URL: Bug Tracker, https://github.com/JupyterPhysSciLab/JupyterPiDAQ_Menu.git/issues
Project-URL: Repository, https://github.com/JupyterPhysSciLab/JupyterPiDAQ_Menu.git.git
Author-email: Jonathan Gutow <gutow@uwosh.edu>
License: BSD 3-Clause License
License-File: LICENSE
License-File: LICENSE.txt
Classifier: Framework :: Jupyter
Classifier: Framework :: Jupyter :: JupyterLab
Classifier: Framework :: Jupyter :: JupyterLab :: 4
Classifier: Framework :: Jupyter :: JupyterLab :: Extensions
Classifier: Framework :: Jupyter :: JupyterLab :: Extensions :: Prebuilt
Classifier: License :: OSI Approved :: BSD License
Classifier: Programming Language :: Python
Classifier: Programming Language :: Python :: 3
Classifier: Programming Language :: Python :: 3.8
Classifier: Programming Language :: Python :: 3.9
Classifier: Programming Language :: Python :: 3.10
Classifier: Programming Language :: Python :: 3.11
Classifier: Programming Language :: Python :: 3.12
Requires-Python: >=3.8
Requires-Dist: jupyter-pandas-gui>=0.9.0
Requires-Dist: jupyterlab<5,>=4.0.0
Requires-Dist: jupyterpidaq>=0.8.1
